mefengl_portal_gun/__init__.py
mefengl_portal_gun/main.py
mefengl_portal_gun-0.1.1.dist-info/WHEEL
mefengl_portal_gun-0.1.1.dist-info/entry_points.txt
mefengl_portal_gun-0.1.1.dist-info/METADATA
mefengl_portal_gun-0.1.1.dist-info/RECORD
